Metadata-Version: 2.4
Name: permamodel
Version: 0.2.3
Summary: Permafrost models with a Basic Model Interface
Author-email: Elchin Jafarov <elchin.jafarov@colorado.edu>, Scott Stewart <scotts@colorado.edu>, Kang Wang <kang.wang@colorado.edu>, Ethan Pierce <ethan.pierce@colorado.edu>, Irina Overeem <irina.overeem@colorado.edu>
Maintainer-email: Mark Piper <mark.piper@colorado.edu>, Eric Hutton <eric.hutton@colorado.edu>
License: MIT License
Project-URL: Homepage, https://permamodel.github.io
Project-URL: Repository, https://github.com/permamodel/permamodel
Keywords: bmi,component modeling,earth science,model coupling,numerical modeling,permafrost
Classifier: Programming Language :: Python :: 3
Classifier: License :: OSI Approved :: MIT License
Classifier: Operating System :: OS Independent
Classifier: Intended Audience :: Developers
Classifier: Intended Audience :: Science/Research
Classifier: Intended Audience :: Education
Requires-Python: >=3.9
License-File: LICENSE
Requires-Dist: affine
Requires-Dist: netCDF4
Requires-Dist: scipy
Requires-Dist: numpy
Requires-Dist: pyyaml
Requires-Dist: python-dateutil
Requires-Dist: toml
Requires-Dist: xarray
Provides-Extra: dev
Requires-Dist: black; extra == "dev"
Requires-Dist: flake8; extra == "dev"
Requires-Dist: isort; extra == "dev"
Requires-Dist: nox; extra == "dev"
Provides-Extra: build
Requires-Dist: build; extra == "build"
Requires-Dist: twine; extra == "build"
Requires-Dist: zest.releaser; extra == "build"
Provides-Extra: testing
Requires-Dist: pytest; extra == "testing"
Requires-Dist: pytest-cov; extra == "testing"
Requires-Dist: coverage[toml]; extra == "testing"
Requires-Dist: coveralls; extra == "testing"
Dynamic: license-file
